mindnlp/__init__.py
mindnlp/cli.py
mindnlp/evaluate.py
mindnlp/peft.py
mindnlp/_csrc/cuda/flash.cu
mindnlp/_csrc/cuda/wkv.cu
mindnlp/accelerate/__init__.py
mindnlp/accelerate/utils/__init__.py
mindnlp/accelerate/utils/modeling.py
mindnlp/data/__init__.py
mindnlp/data/io/__init__.py
mindnlp/data/io/audio.py
mindnlp/dataset/__init__.py
mindnlp/dataset/load.py
mindnlp/dataset/map_fn.py
mindnlp/dataset/utils.py
mindnlp/diffusers/__init__.py
mindnlp/experimental/rwkv6/modeling_rwkv6.py
mindnlp/experimental/rwkv6/sampler_rwkv6.py
mindnlp/experimental/rwkv6/tokenizer_rwkv6.py
mindnlp/quant/__init__.py
mindnlp/quant/mindbnb/__init__.py
mindnlp/quant/mindbnb/bitsandbytes/__init__.py
mindnlp/quant/mindbnb/bitsandbytes/bnbop.py
mindnlp/quant/mindbnb/bitsandbytes/consts.py
mindnlp/quant/mindbnb/bitsandbytes/cuda_specs.py
mindnlp/quant/mindbnb/bitsandbytes/functional.py
mindnlp/quant/mindbnb/bitsandbytes/lib.py
mindnlp/quant/mindbnb/bitsandbytes/utils.py
mindnlp/quant/mindbnb/bitsandbytes/autograd/__init__.py
mindnlp/quant/mindbnb/bitsandbytes/autograd/_functions.py
mindnlp/quant/mindbnb/bitsandbytes/nn/__init__.py
mindnlp/quant/mindbnb/bitsandbytes/nn/modules.py
mindnlp/quant/mindbnb/csrc/kernels.cu
mindnlp/quant/mindbnb/csrc/ops.cu
mindnlp/quant/mindbnb/integrations/__init__.py
mindnlp/quant/mindbnb/integrations/quantization_bnb_8bit.py
mindnlp/quant/mindbnb/integrations/replace_modules.py
mindnlp/quant/mindbnb/tests/test_bitsandbytes_linear.py
mindnlp/quant/mindbnb/tests/test_matmul.py
mindnlp/quant/mindbnb/tests/test_mindbnb_linear.py
mindnlp/quant/mindbnb/tests/test_model.py
mindnlp/quant/smooth_quant/__init__.py
mindnlp/quant/smooth_quant/configs.py
mindnlp/quant/smooth_quant/quant.py
mindnlp/quant/smooth_quant/smooth.py
mindnlp/sentence/__init__.py
mindnlp/timm/__init__.py
mindnlp/transformers/__init__.py
mindnlp/transformers/masking_utils.py
mindnlp/transformers/modeling_utils.py
mindnlp/transformers/tokenization_utils.py
mindnlp/transformers/trainer.py
mindnlp-0.5.1.dist-info/LICENSE
mindnlp-0.5.1.dist-info/METADATA
mindnlp-0.5.1.dist-info/NOTICE
mindnlp-0.5.1.dist-info/WHEEL
mindnlp-0.5.1.dist-info/entry_points.txt
mindnlp-0.5.1.dist-info/top_level.txt
mindnlp-0.5.1.dist-info/RECORD
