Metadata-Version: 2.1
Name: mindnlp
Version: 0.5.1
Summary: An open source natural language processing research tool box. Git version: [sha1]:b0f7439f, [branch]: (HEAD -> 0.5, tag: v0.5.0, ms/0.5)
Home-page: https://github.com/mindlab-ai/mindnlp/tree/master/
Author: MindSpore Team
License: Apache 2.0
Project-URL: Sources, https://github.com/mindlab-ai/mindnlp
Project-URL: Issue Tracker, https://github.com/mindlab-ai/mindnlp/issues
Classifier: License :: OSI Approved :: Apache Software License
License-File: LICENSE
License-File: NOTICE
Requires-Dist: mindspore<=2.7.0,>=2.5.0
Requires-Dist: tqdm
Requires-Dist: requests
Requires-Dist: accelerate>=1.6.0
Requires-Dist: transformers>=4.55.0
Requires-Dist: peft>=0.15.2
Requires-Dist: datasets
Requires-Dist: evaluate
Requires-Dist: tokenizers
Requires-Dist: safetensors
Requires-Dist: diffusers
Requires-Dist: sentencepiece
Requires-Dist: regex
Requires-Dist: addict
Requires-Dist: ml-dtypes
Requires-Dist: pyctcdecode
Requires-Dist: pytest
Requires-Dist: pillow>=10.0.0
Requires-Dist: ftfy
